<?xml version="1.0" encoding="utf-8"?><statistics><movies_by_genre description="What movies are of given genre?"><genre name="Crime"><movie>The Shawshank Redemption</movie><movie>12 Angry Men</movie><movie>The Lord of the Rings: The Fellowship of the Ring</movie></genre><genre name="Drama"><movie>Schindler's List</movie><movie>Il buono, il brutto, il cattivo</movie><movie>Inception</movie></genre><genre name="Fantasy"><movie>The Godfather</movie><movie>Fight Club</movie><movie>The Matrix</movie></genre><genre name="Action"><movie>Star Wars</movie></genre><genre name="Biography"><movie>The Lord of the Rings: The Two Towers</movie><movie>One Flew Over the Cuckoo's Nest</movie><movie>Goodfellas</movie></genre><genre name="Adventure"><movie>The Godfather: Part II</movie><movie>Forrest Gump</movie></genre><genre name="Thriller"></genre><genre name="History"><movie>The Dark Knight</movie><movie>Shichinin no samurai</movie></genre><genre name="Romance"><movie>Pulp Fiction</movie></genre><genre name="Western"><movie>The Lord of the Rings: The Return of the King</movie><movie>Star Wars: Episode V - The Empire Strikes Back</movie></genre></movies_by_genre><movies_count_by_genre description="How many movies are of given genre?"><genre name="Crime">3</genre><genre name="Drama">3</genre><genre name="Fantasy">3</genre><genre name="Action">1</genre><genre name="Biography">3</genre><genre name="Adventure">2</genre><genre name="Thriller">0</genre><genre name="History">2</genre><genre name="Romance">1</genre><genre name="Western">2</genre></movies_count_by_genre><movies_titles_count description="How many titles are registered for given movie?"><movie name="The Shawshank Redemption">2</movie><movie name="The Godfather">2</movie><movie name="The Godfather: Part II">2</movie><movie name="The Dark Knight">2</movie><movie name="12 Angry Men">2</movie><movie name="Schindler's List">2</movie><movie name="Pulp Fiction">1</movie><movie name="The Lord of the Rings: The Return of the King">2</movie><movie name="Il buono, il brutto, il cattivo">2</movie><movie name="Fight Club">2</movie><movie name="The Lord of the Rings: The Fellowship of the Ring">2</movie><movie name="Forrest Gump">1</movie><movie name="Star Wars: Episode V - The Empire Strikes Back">2</movie><movie name="Inception">2</movie><movie name="The Lord of the Rings: The Two Towers">2</movie><movie name="One Flew Over the Cuckoo's Nest">2</movie><movie name="Goodfellas">2</movie><movie name="The Matrix">2</movie><movie name="Shichinin no samurai">2</movie><movie name="Star Wars">2</movie></movies_titles_count><movies_by_original_title_to_locale_id description="What movies have original title in given language?"><locale localeId="en-GB"><movie>The Lord of the Rings: The Return of the King</movie><movie>Fight Club</movie><movie>The Lord of the Rings: The Fellowship of the Ring</movie><movie>Forrest Gump</movie><movie>Star Wars: Episode V - The Empire Strikes Back</movie><movie>Inception</movie><movie>The Lord of the Rings: The Two Towers</movie><movie>One Flew Over the Cuckoo's Nest</movie><movie>Goodfellas</movie><movie>The Matrix</movie><movie>Star Wars</movie></locale><locale localeId="en-US"><movie>The Shawshank Redemption</movie><movie>The Godfather</movie><movie>The Godfather: Part II</movie><movie>The Dark Knight</movie><movie>12 Angry Men</movie><movie>Schindler's List</movie><movie>Pulp Fiction</movie></locale><locale localeId="pl-PL"></locale><locale localeId="es-ES"><movie>Il buono, il brutto, il cattivo</movie></locale><locale localeId="ja-JA"><movie>Shichinin no samurai</movie></locale></movies_by_original_title_to_locale_id><original_titles_count_by_locale_id description="How many movies have original title in given language?"><locale localeId="en-GB">11</locale><locale localeId="en-US">7</locale><locale localeId="pl-PL">0</locale><locale localeId="es-ES">1</locale><locale localeId="ja-JA">1</locale></original_titles_count_by_locale_id><movies_by_year description="Which movies were released in given year?"><year value="1954"><movie>Shichinin no samurai</movie></year><year value="1957"><movie>12 Angry Men</movie></year><year value="1966"><movie>Il buono, il brutto, il cattivo</movie></year><year value="1972"><movie>The Godfather</movie></year><year value="1974"><movie>The Godfather: Part II</movie></year><year value="1975"><movie>One Flew Over the Cuckoo's Nest</movie></year><year value="1977"><movie>Star Wars</movie></year><year value="1980"><movie>Star Wars: Episode V - The Empire Strikes Back</movie><movie>Goodfellas</movie></year><year value="1993"><movie>Schindler's List</movie></year><year value="1994"><movie>The Shawshank Redemption</movie><movie>Pulp Fiction</movie><movie>Forrest Gump</movie></year><year value="1999"><movie>Fight Club</movie><movie>The Matrix</movie></year><year value="2001"><movie>The Lord of the Rings: The Fellowship of the Ring</movie></year><year value="2002"><movie>The Lord of the Rings: The Two Towers</movie></year><year value="2003"><movie>The Lord of the Rings: The Return of the King</movie></year><year value="2008"><movie>The Dark Knight</movie></year><year value="2010"><movie>Inception</movie></year></movies_by_year><movies_count_by_year description="How many movies were released in given year?"><year value="1954">1</year><year value="1957">1</year><year value="1966">1</year><year value="1972">1</year><year value="1974">1</year><year value="1975">1</year><year value="1977">1</year><year value="1980">2</year><year value="1993">1</year><year value="1994">3</year><year value="1999">2</year><year value="2001">1</year><year value="2002">1</year><year value="2003">1</year><year value="2008">1</year><year value="2010">1</year></movies_count_by_year></statistics>